pyelq/__init__.py
pyelq/component/__init__.py
pyelq/component/background.py
pyelq/component/component.py
pyelq/component/error_model.py
pyelq/component/offset.py
pyelq/component/source_model.py
pyelq/coordinate_system.py
pyelq/data_access/__init__.py
pyelq/data_access/data_access.py
pyelq/dispersion_model/__init__.py
pyelq/dispersion_model/gaussian_plume.py
pyelq/dlm.py
pyelq/gas_species.py
pyelq/meteorology.py
pyelq/model.py
pyelq/plotting/__init__.py
pyelq/plotting/plot.py
pyelq/preprocessing.py
pyelq/sensor/__init__.py
pyelq/sensor/beam.py
pyelq/sensor/satellite.py
pyelq/sensor/sensor.py
pyelq/source_map.py
pyelq/support_functions/__init__.py
pyelq/support_functions/post_processing.py
pyelq/support_functions/spatio_temporal_interpolation.py
pyelq-1.1.4.dist-info/LICENSE.md
pyelq-1.1.4.dist-info/LICENSES/Apache-2.0.txt
pyelq-1.1.4.dist-info/METADATA
pyelq-1.1.4.dist-info/WHEEL
pyelq-1.1.4.dist-info/RECORD
