Metadata-Version: 2.3
Name: pyelq
Version: 1.1.4
Summary: Package for detection, localization and quantification code.
License: Apache-2.0
Keywords: gas dispersion,emission,detection,localization,quantification
Author: Bas van de Kerkhof
Requires-Python: >=3.9
Classifier: License :: OSI Approved :: Apache Software License
Classifier: Programming Language :: Python :: 3
Classifier: Programming Language :: Python :: 3.9
Classifier: Programming Language :: Python :: 3.10
Classifier: Programming Language :: Python :: 3.11
Classifier: Programming Language :: Python :: 3.12
Classifier: Programming Language :: Python :: 3.13
Requires-Dist: geojson (>=3.2.0)
Requires-Dist: numpy (>=2.0.2)
Requires-Dist: openmcmc (==1.0.6)
Requires-Dist: pandas (>=2.2.3)
Requires-Dist: plotly (>=6.0.0)
Requires-Dist: pymap3d (>=3.1.0)
Requires-Dist: scikit-learn (>=1.6.1)
Requires-Dist: scipy (>=1.13.1)
Requires-Dist: shapely (>=2.0.7)
Project-URL: Documentation, https://sede-open.github.io/pyELQ/
Project-URL: Homepage, https://sede-open.github.io/pyELQ/
Project-URL: Repository, https://github.com/sede-open/pyELQ
